hypothesis_client/__init__.py
hypothesis_client/hypothesis_client.py
hypothesis_client/token_scraper.py
hypothesis_client-0.0.2.dist-info/METADATA
hypothesis_client-0.0.2.dist-info/RECORD
hypothesis_client-0.0.2.dist-info/WHEEL
hypothesis_client-0.0.2.dist-info/top_level.txt
