Metadata-Version: 2.1
Name: hypothesis-client
Version: 0.0.2
Summary: A Python client for interacting with Hypothes.is API
Home-page: https://github.com/linuxpi/hypothesis_client
Author: Varun Bansal
Author-email: varunb94@gmail.com
License: Apache2
Platform: UNKNOWN
Classifier: Development Status :: 2 - Pre-Alpha
Classifier: Intended Audience :: Developers
Classifier: License :: OSI Approved :: MIT License
Classifier: Operating System :: OS Independent
Classifier: Programming Language :: Python :: 3
Requires-Dist: mechanicalsoup
Requires-Dist: requests
